<?xml version="1.0" encoding="UTF-8"?>
<!DOCTYPE mapper PUBLIC "-//mybatis.org//DTD Mapper 3.0//EN" "http://mybatis.org/dtd/mybatis-3-mapper.dtd">
<mapper namespace="com.deer.wms.produce.manage.dao.ProcessBomMapper">
  <resultMap id="BaseResultMap" type="com.deer.wms.produce.manage.model.ProcessBom">
    <!--
      WARNING - @mbg.generated
    -->
    <id column="id" jdbcType="INTEGER" property="id" />
    <result column="operator_id" jdbcType="INTEGER" property="operatorId" />
    <result column="create_time" jdbcType="TIMESTAMP" property="createTime" />
    <result column="update_time" jdbcType="TIMESTAMP" property="updateTime" />
    <result column="version" jdbcType="INTEGER" property="version" />
    <result column="status" jdbcType="INTEGER" property="status" />
    <result column="process_name" jdbcType="VARCHAR" property="processName" />
    <result column="product_process_id" jdbcType="INTEGER" property="productProcessId" />
    <result column="specification" jdbcType="VARCHAR" property="specification" />
    <result column="process_content" jdbcType="VARCHAR" property="processContent" />
    <result column="process_step" jdbcType="INTEGER" property="processStep" />
    <result column="product_annex_code" jdbcType="VARCHAR" property="productAnnexCode" />
    <result column="memo" jdbcType="VARCHAR" property="memo" />
    <result column="company_id" jdbcType="INTEGER" property="companyId" />
  </resultMap>

    <resultMap id="ProcessBomDTOResultMap" type="com.deer.wms.produce.manage.model.ProcessBomDto">
        <result column="create_time" jdbcType="TIMESTAMP" property="createTime" />
        <result column="update_time" jdbcType="TIMESTAMP" property="updateTime" />
        <result column="process_name" jdbcType="VARCHAR" property="processName" />
        <result column="process_content" jdbcType="VARCHAR" property="processContent" />
        <result column="process_step" jdbcType="INTEGER" property="processStep" />
        <result column="product_annex_code" jdbcType="VARCHAR" property="productAnnexCode" />
        <result column="company_name" jdbcType="VARCHAR" property="companyName" />
        <result column="product_process_name" jdbcType="VARCHAR" property="productProcessName" />
    </resultMap>
</mapper>